README.md
setup.py
transfer_client/__init__.py
transfer_client/cli.py
transfer_client/local.py
transfer_client/stream.py
transfer_client/transfer_client.py
transfer_client/unpack.md
transfer_client.egg-info/PKG-INFO
transfer_client.egg-info/SOURCES.txt
transfer_client.egg-info/dependency_links.txt
transfer_client.egg-info/entry_points.txt
transfer_client.egg-info/requires.txt
transfer_client.egg-info/top_level.txt